wsgi_vmprof.py
wsgi_vmprof-0.0.1.dist-info/DESCRIPTION.rst
wsgi_vmprof-0.0.1.dist-info/METADATA
wsgi_vmprof-0.0.1.dist-info/RECORD
wsgi_vmprof-0.0.1.dist-info/WHEEL
wsgi_vmprof-0.0.1.dist-info/metadata.json
wsgi_vmprof-0.0.1.dist-info/top_level.txt
