Metadata-Version: 2.0
Name: wsgi-vmprof
Version: 0.0.1
Summary: UNKNOWN
Home-page: https://github.com/c-bata/wsgi-vmprof
Author: Masashi Shibata <contact@c-bata.link>
Author-email: contact@c-bata.link
License: MIT License
Keywords: web wsgi vmprof
Platform: UNKNOWN
Classifier: Development Status :: 1 - Planning
Classifier: Intended Audience :: Developers
Classifier: License :: OSI Approved :: MIT License
Classifier: Topic :: Internet :: WWW/HTTP :: WSGI
Classifier: Environment :: Web Environment
Classifier: Programming Language :: Python
Classifier: Programming Language :: Python :: 3
Classifier: Programming Language :: Python :: 3.3
Classifier: Programming Language :: Python :: 3.4
Classifier: Programming Language :: Python :: 3.5
Classifier: Programming Language :: Python :: 3.6
Requires-Dist: vmprof
